surfer_mcp/__init__.py
surfer_mcp/server.py
surfer_mcp-0.1.3.dist-info/METADATA
surfer_mcp-0.1.3.dist-info/WHEEL
surfer_mcp-0.1.3.dist-info/entry_points.txt
surfer_mcp-0.1.3.dist-info/RECORD
