Metadata-Version: 2.4
Name: surfer-mcp
Version: 0.1.3
Summary: This is the official MCP server for Surfer
Author-email: Sahil Lalani <99920148+sahil-lalani@users.noreply.github.com>
Requires-Python: >=3.13
Requires-Dist: chromadb>=0.5.23
Requires-Dist: mcp>=1.1.2
